Metadata-Version: 2.1
Name: napari-seedseg
Version: 0.0.1
Summary: A simple plugin for segmentation
Home-page: https://github.com/rezaakb/napari-seedseg
Author: Reza Akbarian Bafghi
Author-email: reza.akb98@gmail.com
License: BSD-3
Project-URL: Bug Tracker, https://github.com/rezaakb/napari-seedseg/issues
Project-URL: Documentation, https://github.com/rezaakb/napari-seedseg#README.md
Project-URL: Source Code, https://github.com/rezaakb/napari-seedseg
Project-URL: User Support, https://github.com/rezaakb/napari-seedseg/issues
Keywords: example project
Classifier: Development Status :: 2 - Pre-Alpha
Classifier: Framework :: napari
Classifier: Intended Audience :: Developers
Classifier: License :: OSI Approved :: BSD License
Classifier: Operating System :: OS Independent
Classifier: Programming Language :: Python
Classifier: Programming Language :: Python :: 3
Classifier: Programming Language :: Python :: 3 :: Only
Classifier: Programming Language :: Python :: 3.8
Classifier: Programming Language :: Python :: 3.9
Classifier: Programming Language :: Python :: 3.10
Classifier: Topic :: Scientific/Engineering :: Image Processing
Requires-Python: >=3.8
Provides-Extra: testing
License-File: LICENSE
